{
  "features_incremental_epoch_5_20251123_135223": {
    "epoch": 5,
    "algorithm": "features_incremental",
    "metrics": {
      "progress": 0.1111111111111111
    },
    "timestamp": "20251123_135223",
    "model_path": null
  },
  "features_incremental_epoch_10_20251123_135233": {
    "epoch": 10,
    "algorithm": "features_incremental",
    "metrics": {
      "progress": 0.2222222222222222
    },
    "timestamp": "20251123_135233",
    "model_path": null
  },
  "features_incremental_epoch_15_20251123_135241": {
    "epoch": 15,
    "algorithm": "features_incremental",
    "metrics": {
      "progress": 0.3333333333333333
    },
    "timestamp": "20251123_135241",
    "model_path": null
  },
  "features_incremental_epoch_20_20251123_135300": {
    "epoch": 20,
    "algorithm": "features_incremental",
    "metrics": {
      "progress": 0.4444444444444444
    },
    "timestamp": "20251123_135300",
    "model_path": null
  },
  "features_incremental_epoch_25_20251123_135312": {
    "epoch": 25,
    "algorithm": "features_incremental",
    "metrics": {
      "progress": 0.5555555555555556
    },
    "timestamp": "20251123_135312",
    "model_path": null
  },
  "features_incremental_epoch_30_20251123_135323": {
    "epoch": 30,
    "algorithm": "features_incremental",
    "metrics": {
      "progress": 0.6666666666666666
    },
    "timestamp": "20251123_135323",
    "model_path": null
  },
  "features_incremental_epoch_35_20251123_135330": {
    "epoch": 35,
    "algorithm": "features_incremental",
    "metrics": {
      "progress": 0.7777777777777778
    },
    "timestamp": "20251123_135330",
    "model_path": null
  },
  "features_incremental_epoch_40_20251123_135336": {
    "epoch": 40,
    "algorithm": "features_incremental",
    "metrics": {
      "progress": 0.8888888888888888
    },
    "timestamp": "20251123_135336",
    "model_path": null
  },
  "features_incremental_epoch_45_20251123_135348": {
    "epoch": 45,
    "algorithm": "features_incremental",
    "metrics": {
      "progress": 1.0
    },
    "timestamp": "20251123_135348",
    "model_path": null
  },
  "features_epoch_0_20251123_135348": {
    "epoch": 0,
    "algorithm": "features",
    "metrics": {},
    "timestamp": "20251123_135348",
    "model_path": null
  },
  "xgboost_epoch_12_20251123_135348": {
    "epoch": 12,
    "algorithm": "xgboost",
    "metrics": {
      "train_accuracy": 1.0,
      "val_accuracy": 0.42857142857142855,
      "best_iteration": 12,
      "test_accuracy": 0.5714285714285714,
      "test_accuracy_yellow": 1.0,
      "test_accuracy_green": 0.0,
      "test_accuracy_purple": 1.0,
      "confusion_matrix": [
        [
          2,
          0,
          0
        ],
        [
          0,
          0,
          3
        ],
        [
          0,
          0,
          2
        ]
      ],
      "classification_report": {
        "yellow": {
          "precision": 1.0,
          "recall": 1.0,
          "f1-score": 1.0,
          "support": 2.0
        },
        "green": {
          "precision": 0.0,
          "recall": 0.0,
          "f1-score": 0.0,
          "support": 3.0
        },
        "purple": {
          "precision": 0.4,
          "recall": 1.0,
          "f1-score": 0.5714285714285714,
          "support": 2.0
        },
        "accuracy": 0.5714285714285714,
        "macro avg": {
          "precision": 0.4666666666666666,
          "recall": 0.6666666666666666,
          "f1-score": 0.5238095238095238,
          "support": 7.0
        },
        "weighted avg": {
          "precision": 0.39999999999999997,
          "recall": 0.5714285714285714,
          "f1-score": 0.4489795918367347,
          "support": 7.0
        }
      }
    },
    "timestamp": "20251123_135348",
    "model_path": "models/checkpoints/xgboost_epoch_12_20251123_135348.pkl"
  }
}